pyesp/__init__.py
pyesp/pyesp.py
pyesp/run.py
pyesp/data/api/mpython.json
pyesp/data/api/nodemcu.json
pyesp/data/serial/config.json
pyesp-0.7.3.dist-info/DESCRIPTION.rst
pyesp-0.7.3.dist-info/METADATA
pyesp-0.7.3.dist-info/RECORD
pyesp-0.7.3.dist-info/WHEEL
pyesp-0.7.3.dist-info/entry_points.txt
pyesp-0.7.3.dist-info/metadata.json
pyesp-0.7.3.dist-info/top_level.txt
