Metadata-Version: 2.0
Name: pyesp
Version: 0.7.3
Summary: tool for programming/comunicate with ESP8266 platforms based on MircoPython and NodeMCU
Home-page: https://github.com/LeftRadio/pyesp
Author: Vladislav Kamenev
Author-email: wladkam@mail.com
License: MIT
Platform: UNKNOWN
Classifier: Development Status :: 4 - Beta
Classifier: Topic :: Utilities
Classifier: Programming Language :: Python :: 3
